palmfrog/__init__.py
palmfrog/main.py
palmfrog-1.0.2.dist-info/METADATA
palmfrog-1.0.2.dist-info/WHEEL
palmfrog-1.0.2.dist-info/entry_points.txt
palmfrog-1.0.2.dist-info/top_level.txt
palmfrog-1.0.2.dist-info/RECORD
