Metadata-Version: 2.1
Name: palmfrog
Version: 1.0.2
Summary: ChatGPT for terminal applications with palmfrog.net website.
Author: Palmfrog
Author-email: hello@palmfrog.net
License: MIT
Keywords: chatgpt terminal chatbot palmfrog camouflage
Requires-Dist: requests
Requires-Dist: pycryptodome
Requires-Dist: colorama
